vllm_omni/__init__.py
vllm_omni/logger.py
vllm_omni/outputs.py
vllm_omni/patch.py
vllm_omni/request.py
vllm_omni/version.py
vllm_omni/assets/video.py
vllm_omni/benchmarks/serve.py
vllm_omni/benchmarks/data_modules/__init__.py
vllm_omni/benchmarks/data_modules/random_multi_modal_dataset.py
vllm_omni/benchmarks/metrics/__init__.py
vllm_omni/benchmarks/metrics/metrics.py
vllm_omni/benchmarks/patch/__init__.py
vllm_omni/benchmarks/patch/patch.py
vllm_omni/config/__init__.py
vllm_omni/config/lora.py
vllm_omni/config/model.py
vllm_omni/core/__init__.py
vllm_omni/core/sched/__init__.py
vllm_omni/core/sched/omni_ar_scheduler.py
vllm_omni/core/sched/omni_generation_scheduler.py
vllm_omni/core/sched/output.py
vllm_omni/diffusion/__init__.py
vllm_omni/diffusion/compile.py
vllm_omni/diffusion/data.py
vllm_omni/diffusion/diffusion_engine.py
vllm_omni/diffusion/envs.py
vllm_omni/diffusion/forward_context.py
vllm_omni/diffusion/offload.py
vllm_omni/diffusion/registry.py
vllm_omni/diffusion/request.py
vllm_omni/diffusion/scheduler.py
vllm_omni/diffusion/attention/__init__.py
vllm_omni/diffusion/attention/layer.py
vllm_omni/diffusion/attention/selector.py
vllm_omni/diffusion/attention/backends/__init__.py
vllm_omni/diffusion/attention/backends/abstract.py
vllm_omni/diffusion/attention/backends/flash_attn.py
vllm_omni/diffusion/attention/backends/registry.py
vllm_omni/diffusion/attention/backends/ring_flash_attn.py
vllm_omni/diffusion/attention/backends/ring_pytorch_attn.py
vllm_omni/diffusion/attention/backends/sage_attn.py
vllm_omni/diffusion/attention/backends/sdpa.py
vllm_omni/diffusion/attention/backends/ring/__init__.py
vllm_omni/diffusion/attention/backends/ring/ring_globals.py
vllm_omni/diffusion/attention/backends/ring/ring_kernels.py
vllm_omni/diffusion/attention/backends/ring/ring_selector.py
vllm_omni/diffusion/attention/backends/ring/ring_utils.py
vllm_omni/diffusion/attention/backends/utils/__init__.py
vllm_omni/diffusion/attention/backends/utils/fa.py
vllm_omni-0.14.0.dist-info/licenses/LICENSE
vllm_omni-0.14.0.dist-info/METADATA
vllm_omni-0.14.0.dist-info/WHEEL
vllm_omni-0.14.0.dist-info/entry_points.txt
vllm_omni-0.14.0.dist-info/top_level.txt
vllm_omni-0.14.0.dist-info/RECORD
