Metadata-Version: 2.4
Name: vllm-omni
Version: 0.14.0
Summary: A framework for efficient model inference with omni-modality models
Author: vLLM-Omni Team
License: Apache-2.0
Project-URL: Homepage, https://github.com/vllm-project/vllm-omni
Project-URL: Repository, https://github.com/vllm-project/vllm-omni
Project-URL: Documentation, https://vllm-omni.readthedocs.io
Project-URL: Bug Tracker, https://github.com/vllm-project/vllm-omni/issues
Keywords: vllm,multimodal,diffusion,transformer,inference,serving
Classifier: Development Status :: 3 - Alpha
Classifier: Intended Audience :: Developers
Classifier: Intended Audience :: Science/Research
Classifier: License :: OSI Approved :: Apache Software License
Classifier: Programming Language :: Python :: 3.10
Classifier: Programming Language :: Python :: 3.11
Classifier: Programming Language :: Python :: 3.12
Classifier: Programming Language :: Python :: 3.13
Classifier: Topic :: Scientific/Engineering :: Artificial Intelligence
Classifier: Topic :: Software Development :: Libraries :: Python Modules
Requires-Python: <3.14,>=3.10
License-File: LICENSE
Requires-Dist: omegaconf>=2.3.0
Requires-Dist: librosa>=0.11.0
Requires-Dist: resampy>=0.4.3
Requires-Dist: diffusers>=0.36.0
Requires-Dist: accelerate==1.12.0
Requires-Dist: gradio==5.50
Requires-Dist: soundfile>=0.13.1
Requires-Dist: cache-dit==1.2.0
Requires-Dist: tqdm>=4.66.0
Requires-Dist: torchsde>=0.2.6
Requires-Dist: fa3-fwd==0.0.1
Requires-Dist: openai-whisper>=20250625
Requires-Dist: imageio[ffmpeg]>=2.37.2
Requires-Dist: onnxruntime>=1.19.0
Requires-Dist: sox>=1.5.0
Provides-Extra: dev
Requires-Dist: pytest>=7.0.0; extra == "dev"
Requires-Dist: pytest-asyncio>=0.21.0; extra == "dev"
Requires-Dist: pytest-cov>=4.0.0; extra == "dev"
Requires-Dist: mypy==1.11.1; extra == "dev"
Requires-Dist: pre-commit==4.0.1; extra == "dev"
Requires-Dist: openai-whisper>=20250625; extra == "dev"
Requires-Dist: psutil>=7.2.0; extra == "dev"
Requires-Dist: soundfile>=0.13.1; extra == "dev"
Requires-Dist: imageio[ffmpeg]>=0.6.0; extra == "dev"
Requires-Dist: opencv-python>=4.12.0.88; extra == "dev"
Provides-Extra: docs
Requires-Dist: mkdocs>=1.5.0; extra == "docs"
Requires-Dist: mkdocs-api-autonav; extra == "docs"
Requires-Dist: mkdocs-material; extra == "docs"
Requires-Dist: mkdocstrings-python; extra == "docs"
Requires-Dist: mkdocs-gen-files; extra == "docs"
Requires-Dist: mkdocs-awesome-nav; extra == "docs"
Requires-Dist: mkdocs-glightbox; extra == "docs"
Requires-Dist: mkdocs-git-revision-date-localized-plugin; extra == "docs"
Requires-Dist: mkdocs-minify-plugin; extra == "docs"
Requires-Dist: regex; extra == "docs"
Requires-Dist: ruff; extra == "docs"
Requires-Dist: pydantic; extra == "docs"
Dynamic: license-file
